pynabapi/__init__.py
pynabapi/exceptions.py
pynabapi/helpers.py
pynabapi/ynab.py
pynabapi/model/__init__.py
pynabapi/model/account.py
pynabapi/model/budget.py
pynabapi/model/budgetmonth.py
pynabapi/model/category.py
pynabapi/model/payee.py
pynabapi/model/transaction.py
pynab_client-0.2.dist-info/LICENSE.txt
pynab_client-0.2.dist-info/METADATA
pynab_client-0.2.dist-info/WHEEL
pynab_client-0.2.dist-info/top_level.txt
pynab_client-0.2.dist-info/RECORD
