Metadata-Version: 2.1
Name: pynab-client
Version: 0.2
Summary: Python API to access YNAB v1 API
Home-page: https://github.com/irunasroot/pynab-client
Author: Dennis Whitney
Author-email: dennis@irunasroot.com
License: GNU GPLv3
Download-URL: https://github.com/irunasroot/pynab-client/archive/v0.2.tar.gz
Keywords: ynab,pynab,budgeting,budgets,youneedabudget
Platform: UNKNOWN
Classifier: Development Status :: 4 - Beta
Classifier: Intended Audience :: Developers
Classifier: Topic :: Software Development :: Build Tools
Classifier: License :: OSI Approved :: GNU General Public License v3 (GPLv3)
Classifier: Programming Language :: Python :: 3.6
Requires-Dist: requests
